{
  "pages": [
    {
      "page": 1,
      "width": 595.303937,
      "height": 841.889764,
      "words": [
        {
          "text": "22",
          "xMin": 433.3,
          "yMin": 21.381,
          "xMax": 446.72,
          "yMax": 33.381
        },
        {
          "text": "岁",
          "xMin": 449.1,
          "yMin": 21.381,
          "xMax": 461.1,
          "yMax": 33.381
        },
        {
          "text": "俞",
          "xMin": 158.05,
          "yMin": 31.641,
          "xMax": 184.05,
          "yMax": 57.641
        },
        {
          "text": "孟",
          "xMin": 197.024,
          "yMin": 31.641,
          "xMax": 223.024,
          "yMax": 57.641
        },
        {
          "text": "瑶",
          "xMin": 235.998,
          "yMin": 31.641,
          "xMax": 261.998,
          "yMax": 57.641
        },
        {
          "text": "广东省广州市",
          "xMin": 433.3,
          "yMin": 43.381,
          "xMax": 505.3,
          "yMax": 55.381
        },
        {
          "text": "求职意向：市场营销专员",
          "xMin": 159.45,
          "yMin": 74.241,
          "xMax": 280.45,
          "yMax": 85.241
        },
        {
          "text": "13500000000",
          "xMin": 433.3,
          "yMin": 65.381,
          "xMax": 507.124,
          "yMax": 77.381
        },
        {
          "text": "service@qq.com",
          "xMin": 433.3,
          "yMin": 87.381,
          "xMax": 517.168,
          "yMax": 99.381
        },
        {
          "text": "自我评价",
          "xMin": 55.9,
          "yMin": 158.361,
          "xMax": 111.9,
          "yMax": 172.361
        },
        {
          "text": "本人是市场营销专业毕业生，有丰富的营销知识体系做基础；对于市场营销",
          "xMin": 160.1,
          "yMin": 163.881,
          "xMax": 556.1,
          "yMax": 175.881
        },
        {
          "text": "方面的前沿和动向有一定的了解，善于分析和吸取经验；熟悉网络推广，尤",
          "xMin": 160.1,
          "yMin": 183.881,
          "xMax": 556.1,
          "yMax": 195.881
        },
        {
          "text": "其是社会化媒体方面，有独到的见解和经验；",
          "xMin": 160.1,
          "yMin": 203.881,
          "xMax": 400.1,
          "yMax": 215.881
        },
        {
          "text": "工作经历",
          "xMin": 53.3,
          "yMin": 246.211,
          "xMax": 109.3,
          "yMax": 260.211
        },
        {
          "text": "2016.4-至今",
          "xMin": 160.3,
          "yMin": 247.981,
          "xMax": 224.7,
          "yMax": 259.981
        },
        {
          "text": "",
          "xMin": 138.25,
          "yMin": 270.575,
          "xMax": 147.202,
          "yMax": 283.871
        },
        {
          "text": "卓望信息有限公司",
          "xMin": 266.7,
          "yMin": 247.981,
          "xMax": 362.7,
          "yMax": 259.981
        },
        {
          "text": "运营推广主管",
          "xMin": 416.64,
          "yMin": 247.981,
          "xMax": 488.64,
          "yMax": 259.981
        },
        {
          "text": "负责社会化媒体营销团队的搭建工作，制定相关运营策略和指标，带领团队",
          "xMin": 159.25,
          "yMin": 271.031,
          "xMax": 555.25,
          "yMax": 283.031
        },
        {
          "text": "实施计划；",
          "xMin": 159.25,
          "yMin": 293.031,
          "xMax": 219.25,
          "yMax": 305.031
        },
        {
          "text": "",
          "xMin": 138.25,
          "yMin": 314.575,
          "xMax": 147.202,
          "yMax": 327.871
        },
        {
          "text": "网站常态运营活动规划和推进执行；",
          "xMin": 159.25,
          "yMin": 315.031,
          "xMax": 351.25,
          "yMax": 327.031
        },
        {
          "text": "",
          "xMin": 138.25,
          "yMin": 336.575,
          "xMax": 147.202,
          "yMax": 349.871
        },
        {
          "text": "相关数据报告和统计，为公司决策层提供决策依据；",
          "xMin": 159.25,
          "yMin": 337.031,
          "xMax": 435.25,
          "yMax": 349.031
        },
        {
          "text": "",
          "xMin": 138.25,
          "yMin": 358.575,
          "xMax": 147.202,
          "yMax": 371.871
        },
        {
          "text": "轻量级产品和应用的策划，统筹产品、技术团队成员实施；",
          "xMin": 159.25,
          "yMin": 359.031,
          "xMax": 471.25,
          "yMax": 371.031
        },
        {
          "text": "2015.4-2016.3",
          "xMin": 160.3,
          "yMin": 388.331,
          "xMax": 237.374,
          "yMax": 400.331
        },
        {
          "text": "广州阿曼莎活动有限公司",
          "xMin": 267.35,
          "yMin": 388.331,
          "xMax": 399.35,
          "yMax": 400.331
        },
        {
          "text": "市场推广专员",
          "xMin": 417.35,
          "yMin": 388.331,
          "xMax": 489.35,
          "yMax": 400.331
        },
        {
          "text": "",
          "xMin": 138.25,
          "yMin": 410.925,
          "xMax": 147.202,
          "yMax": 424.221
        },
        {
          "text": "网络推广渠道搭建维护，包括",
          "xMin": 159.25,
          "yMin": 411.381,
          "xMax": 315.25,
          "yMax": 423.381
        },
        {
          "text": "QQ",
          "xMin": 317.65,
          "yMin": 411.381,
          "xMax": 332.65,
          "yMax": 423.381
        },
        {
          "text": "空间、微博、豆瓣等；",
          "xMin": 335.05,
          "yMin": 411.381,
          "xMax": 455.05,
          "yMax": 423.381
        },
        {
          "text": "",
          "xMin": 138.25,
          "yMin": 432.925,
          "xMax": 147.202,
          "yMax": 446.221
        },
        {
          "text": "负责软硬广投放，网络舆情监控，公关稿撰写，事件营销策划；",
          "xMin": 159.25,
          "yMin": 433.381,
          "xMax": 495.25,
          "yMax": 445.381
        },
        {
          "text": "2014.3-20153",
          "xMin": 160.3,
          "yMin": 464.631,
          "xMax": 233.924,
          "yMax": 476.631
        },
        {
          "text": "华润置地有限公司",
          "xMin": 269.938,
          "yMin": 464.631,
          "xMax": 365.938,
          "yMax": 476.631
        },
        {
          "text": "实习生",
          "xMin": 419.95,
          "yMin": 464.631,
          "xMax": 455.95,
          "yMax": 476.631
        },
        {
          "text": "",
          "xMin": 138.25,
          "yMin": 487.225,
          "xMax": 147.202,
          "yMax": 500.521
        },
        {
          "text": "协助项目主策划的策划工作，梳理文案，制作报表，处理日常办公事物；",
          "xMin": 159.25,
          "yMin": 487.681,
          "xMax": 543.25,
          "yMax": 499.681
        },
        {
          "text": "",
          "xMin": 138.25,
          "yMin": 509.225,
          "xMax": 147.202,
          "yMax": 522.521
        },
        {
          "text": "独立完成历时",
          "xMin": 159.25,
          "yMin": 509.681,
          "xMax": 231.43,
          "yMax": 521.681
        },
        {
          "text": "14",
          "xMin": 234.15,
          "yMin": 509.681,
          "xMax": 247.566,
          "yMax": 521.681
        },
        {
          "text": "天，200",
          "xMin": 250.0,
          "yMin": 509.681,
          "xMax": 294.262,
          "yMax": 521.681
        },
        {
          "text": "名人员安排，预算",
          "xMin": 296.75,
          "yMin": 509.681,
          "xMax": 393.002,
          "yMax": 521.681
        },
        {
          "text": "34",
          "xMin": 395.8,
          "yMin": 509.681,
          "xMax": 409.216,
          "yMax": 521.681
        },
        {
          "text": "万的商业房交会行销活动策",
          "xMin": 411.65,
          "yMin": 509.681,
          "xMax": 556.046,
          "yMax": 521.681
        },
        {
          "text": "划案，受领导称赞。",
          "xMin": 159.25,
          "yMin": 531.681,
          "xMax": 267.25,
          "yMax": 543.681
        },
        {
          "text": "教育背景",
          "xMin": 55.8,
          "yMin": 578.661,
          "xMax": 111.8,
          "yMax": 592.661
        },
        {
          "text": "2013.6-20173",
          "xMin": 160.3,
          "yMin": 581.681,
          "xMax": 233.924,
          "yMax": 593.681
        },
        {
          "text": "武汉科技大学",
          "xMin": 269.938,
          "yMin": 581.681,
          "xMax": 341.938,
          "yMax": 593.681
        },
        {
          "text": "市场营销（本科）",
          "xMin": 425.89,
          "yMin": 581.681,
          "xMax": 521.89,
          "yMax": 593.681
        },
        {
          "text": "基本会计、统计学、市场营销、国际市场营销、市场调查与预测、商业心理",
          "xMin": 159.25,
          "yMin": 604.731,
          "xMax": 555.25,
          "yMax": 616.731
        },
        {
          "text": "学、广告学、公共关系学、货币银行学、经济法、国际贸易、大学英语、经",
          "xMin": 159.25,
          "yMin": 626.731,
          "xMax": 555.25,
          "yMax": 638.731
        },
        {
          "text": "济数学、计算机应用等。",
          "xMin": 159.25,
          "yMin": 648.731,
          "xMax": 291.25,
          "yMax": 660.731
        },
        {
          "text": "技能证书",
          "xMin": 56.65,
          "yMin": 696.011,
          "xMax": 112.65,
          "yMax": 710.011
        },
        {
          "text": "CET-6,优秀的听说写能力",
          "xMin": 161.25,
          "yMin": 702.931,
          "xMax": 294.5,
          "yMax": 714.931
        },
        {
          "text": "计算机二级，熟悉计算机各项操作",
          "xMin": 161.25,
          "yMin": 724.931,
          "xMax": 341.25,
          "yMax": 736.931
        },
        {
          "text": "高级营销员，国家职业资格四级",
          "xMin": 161.25,
          "yMin": 746.931,
          "xMax": 329.25,
          "yMax": 758.931
        }
      ]
    }
  ]
}