{
  "pages": [
    {
      "page": 1,
      "width": 595.303937,
      "height": 841.889764,
      "words": [
        {
          "text": "教育背景",
          "xMin": 223.9,
          "yMin": 38.031,
          "xMax": 279.9,
          "yMax": 52.591
        },
        {
          "text": "2013.09",
          "xMin": 223.85,
          "yMin": 74.621,
          "xMax": 272.25,
          "yMax": 86.061
        },
        {
          "text": "--",
          "xMin": 277.75,
          "yMin": 74.621,
          "xMax": 285.065,
          "yMax": 86.061
        },
        {
          "text": "2017.06",
          "xMin": 290.55,
          "yMin": 74.621,
          "xMax": 338.95,
          "yMax": 86.061
        },
        {
          "text": "湖北工业大学",
          "xMin": 366.395,
          "yMin": 74.621,
          "xMax": 432.329,
          "yMax": 86.061
        },
        {
          "text": "企业管理专业",
          "xMin": 476.296,
          "yMin": 74.621,
          "xMax": 542.296,
          "yMax": 86.061
        },
        {
          "text": "/",
          "xMin": 547.95,
          "yMin": 74.621,
          "xMax": 551.008,
          "yMax": 86.061
        },
        {
          "text": "湖北工业大学",
          "xMin": 366.395,
          "yMin": 116.621,
          "xMax": 432.329,
          "yMax": 128.061
        },
        {
          "text": "平面设计专业",
          "xMin": 476.296,
          "yMin": 116.621,
          "xMax": 542.296,
          "yMax": 128.061
        },
        {
          "text": "/",
          "xMin": 547.95,
          "yMin": 116.621,
          "xMax": 551.008,
          "yMax": 128.061
        },
        {
          "text": "本科",
          "xMin": 223.85,
          "yMin": 92.621,
          "xMax": 245.85,
          "yMax": 104.061
        },
        {
          "text": "2013.09",
          "xMin": 223.85,
          "yMin": 116.621,
          "xMax": 272.25,
          "yMax": 128.061
        },
        {
          "text": "--",
          "xMin": 277.75,
          "yMin": 116.621,
          "xMax": 285.065,
          "yMax": 128.061
        },
        {
          "text": "2017.06",
          "xMin": 290.55,
          "yMin": 116.621,
          "xMax": 338.95,
          "yMax": 128.061
        },
        {
          "text": "选修",
          "xMin": 223.85,
          "yMin": 134.621,
          "xMax": 245.85,
          "yMax": 146.061
        },
        {
          "text": "工作经历",
          "xMin": 223.9,
          "yMin": 149.381,
          "xMax": 279.9,
          "yMax": 163.941
        },
        {
          "text": "2013.09",
          "xMin": 223.85,
          "yMin": 185.971,
          "xMax": 272.25,
          "yMax": 197.411
        },
        {
          "text": "--",
          "xMin": 277.75,
          "yMin": 185.971,
          "xMax": 285.065,
          "yMax": 197.411
        },
        {
          "text": "2017.06",
          "xMin": 290.55,
          "yMin": 185.971,
          "xMax": 338.95,
          "yMax": 197.411
        },
        {
          "text": "明小星",
          "xMin": 50.45,
          "yMin": 192.761,
          "xMax": 110.45,
          "yMax": 217.901
        },
        {
          "text": "武汉云印网络科技有限公司",
          "xMin": 366.395,
          "yMin": 185.971,
          "xMax": 498.373,
          "yMax": 197.411
        },
        {
          "text": "策划专",
          "xMin": 531.307,
          "yMin": 185.971,
          "xMax": 564.307,
          "yMax": 197.411
        },
        {
          "text": "员",
          "xMin": 223.85,
          "yMin": 203.971,
          "xMax": 234.85,
          "yMax": 215.411
        },
        {
          "text": "求职意向：平面/网页设计师",
          "xMin": 19.1,
          "yMin": 222.951,
          "xMax": 141.85,
          "yMax": 233.351
        },
        {
          "text": "工作描述：",
          "xMin": 223.85,
          "yMin": 227.971,
          "xMax": 278.85,
          "yMax": 239.411
        },
        {
          "text": "1.",
          "xMin": 280.85,
          "yMin": 245.971,
          "xMax": 290.772,
          "yMax": 257.411
        },
        {
          "text": "项目进行期，能够制定短期目标，引导团队成员完成",
          "xMin": 307.85,
          "yMin": 245.971,
          "xMax": 560.85,
          "yMax": 257.411
        },
        {
          "text": "各项任务，来进行项目进度管理；",
          "xMin": 259.85,
          "yMin": 263.971,
          "xMax": 424.85,
          "yMax": 275.411
        },
        {
          "text": "基",
          "xMin": 37.3,
          "yMin": 281.073,
          "xMax": 51.3,
          "yMax": 298.671
        },
        {
          "text": "础",
          "xMin": 57.292,
          "yMin": 281.073,
          "xMax": 71.292,
          "yMax": 298.671
        },
        {
          "text": "信",
          "xMin": 77.284,
          "yMin": 281.073,
          "xMax": 91.284,
          "yMax": 298.671
        },
        {
          "text": "息",
          "xMin": 97.276,
          "yMin": 281.073,
          "xMax": 111.276,
          "yMax": 298.671
        },
        {
          "text": "2.",
          "xMin": 280.85,
          "yMin": 281.971,
          "xMax": 290.772,
          "yMax": 293.411
        },
        {
          "text": "负责项目的推广，内测期利用微博与讲座结合获得",
          "xMin": 307.85,
          "yMin": 281.971,
          "xMax": 549.85,
          "yMax": 293.411
        },
        {
          "text": "310",
          "xMin": 259.85,
          "yMin": 299.971,
          "xMax": 282.95,
          "yMax": 311.411
        },
        {
          "text": "客户；",
          "xMin": 285.15,
          "yMin": 299.971,
          "xMax": 318.15,
          "yMax": 311.411
        },
        {
          "text": "",
          "xMin": 57.85,
          "yMin": 324.972,
          "xMax": 65.683,
          "yMax": 336.606
        },
        {
          "text": "出生年月：",
          "xMin": 81.85,
          "yMin": 325.686,
          "xMax": 148.714,
          "yMax": 336.606
        },
        {
          "text": "1991.",
          "xMin": 36.85,
          "yMin": 350.686,
          "xMax": 68.371,
          "yMax": 361.606
        },
        {
          "text": "07",
          "xMin": 134.15,
          "yMin": 350.686,
          "xMax": 148.85,
          "yMax": 361.606
        },
        {
          "text": "",
          "xMin": 57.85,
          "yMin": 374.972,
          "xMax": 65.683,
          "yMax": 386.606
        },
        {
          "text": "政治面貌：中",
          "xMin": 81.85,
          "yMin": 375.686,
          "xMax": 148.787,
          "yMax": 386.606
        },
        {
          "text": "共",
          "xMin": 36.85,
          "yMin": 400.686,
          "xMax": 47.35,
          "yMax": 411.606
        },
        {
          "text": "党",
          "xMin": 87.6,
          "yMin": 400.686,
          "xMax": 98.1,
          "yMax": 411.606
        },
        {
          "text": "策划总",
          "xMin": 531.307,
          "yMin": 335.971,
          "xMax": 564.307,
          "yMax": 347.411
        },
        {
          "text": "监",
          "xMin": 223.85,
          "yMin": 353.971,
          "xMax": 234.85,
          "yMax": 365.411
        },
        {
          "text": "工作描述：",
          "xMin": 223.85,
          "yMin": 377.971,
          "xMax": 278.85,
          "yMax": 389.411
        },
        {
          "text": "1.",
          "xMin": 280.85,
          "yMin": 395.971,
          "xMax": 290.772,
          "yMax": 407.411
        },
        {
          "text": "员",
          "xMin": 138.35,
          "yMin": 400.686,
          "xMax": 148.85,
          "yMax": 411.606
        },
        {
          "text": "工作经",
          "xMin": 81.85,
          "yMin": 425.686,
          "xMax": 116.122,
          "yMax": 436.606
        },
        {
          "text": "验",
          "xMin": 117.55,
          "yMin": 425.686,
          "xMax": 128.05,
          "yMax": 436.606
        },
        {
          "text": "：2",
          "xMin": 129.45,
          "yMin": 425.686,
          "xMax": 148.85,
          "yMax": 436.606
        },
        {
          "text": "年",
          "xMin": 36.85,
          "yMin": 450.686,
          "xMax": 47.35,
          "yMax": 461.606
        },
        {
          "text": "销",
          "xMin": 87.6,
          "yMin": 450.686,
          "xMax": 98.1,
          "yMax": 461.606
        },
        {
          "text": "售",
          "xMin": 138.336,
          "yMin": 450.686,
          "xMax": 148.836,
          "yMax": 461.606
        },
        {
          "text": "",
          "xMin": 57.85,
          "yMin": 474.972,
          "xMax": 65.683,
          "yMax": 486.606
        },
        {
          "text": "方",
          "xMin": 77.284,
          "yMin": 475.823,
          "xMax": 91.284,
          "yMax": 493.421
        },
        {
          "text": "最高学历：大",
          "xMin": 81.85,
          "yMin": 475.686,
          "xMax": 148.787,
          "yMax": 486.606
        },
        {
          "text": "联",
          "xMin": 37.3,
          "yMin": 475.823,
          "xMax": 51.3,
          "yMax": 493.421
        },
        {
          "text": "系",
          "xMin": 57.292,
          "yMin": 475.823,
          "xMax": 71.292,
          "yMax": 493.421
        },
        {
          "text": "式",
          "xMin": 97.276,
          "yMin": 475.823,
          "xMax": 111.276,
          "yMax": 493.421
        },
        {
          "text": "学",
          "xMin": 36.85,
          "yMin": 500.686,
          "xMax": 47.35,
          "yMax": 511.606
        },
        {
          "text": "本",
          "xMin": 87.586,
          "yMin": 500.686,
          "xMax": 98.086,
          "yMax": 511.606
        },
        {
          "text": "",
          "xMin": 57.85,
          "yMin": 524.972,
          "xMax": 65.683,
          "yMax": 536.606
        },
        {
          "text": "武汉云印网络科技有限公司",
          "xMin": 366.395,
          "yMin": 335.971,
          "xMax": 498.373,
          "yMax": 347.411
        },
        {
          "text": "项目进行期，能够制定短期目标，引导团队成员完成",
          "xMin": 307.85,
          "yMin": 395.971,
          "xMax": 560.85,
          "yMax": 407.411
        },
        {
          "text": "各项任务，来进行项目进度管理；",
          "xMin": 259.85,
          "yMin": 413.971,
          "xMax": 424.85,
          "yMax": 425.411
        },
        {
          "text": "",
          "xMin": 57.85,
          "yMin": 424.972,
          "xMax": 65.683,
          "yMax": 436.606
        },
        {
          "text": "电",
          "xMin": 18.85,
          "yMin": 520.236,
          "xMax": 29.35,
          "yMax": 531.156
        },
        {
          "text": "2013.09",
          "xMin": 223.85,
          "yMin": 335.971,
          "xMax": 272.25,
          "yMax": 347.411
        },
        {
          "text": "--",
          "xMin": 277.75,
          "yMin": 335.971,
          "xMax": 285.065,
          "yMax": 347.411
        },
        {
          "text": "2017.06",
          "xMin": 290.55,
          "yMin": 335.971,
          "xMax": 338.95,
          "yMax": 347.411
        },
        {
          "text": "话",
          "xMin": 67.938,
          "yMin": 520.236,
          "xMax": 78.438,
          "yMax": 531.156
        },
        {
          "text": "科",
          "xMin": 138.322,
          "yMin": 500.686,
          "xMax": 148.822,
          "yMax": 511.606
        },
        {
          "text": "：",
          "xMin": 117.025,
          "yMin": 520.236,
          "xMax": 127.525,
          "yMax": 531.156
        },
        {
          "text": "求职意向：市",
          "xMin": 81.85,
          "yMin": 525.686,
          "xMax": 148.85,
          "yMax": 536.606
        },
        {
          "text": "152000000000",
          "xMin": 18.85,
          "yMin": 545.236,
          "xMax": 107.05,
          "yMax": 556.156
        },
        {
          "text": "场",
          "xMin": 36.85,
          "yMin": 550.686,
          "xMax": 47.35,
          "yMax": 561.606
        },
        {
          "text": "专",
          "xMin": 87.6,
          "yMin": 550.686,
          "xMax": 98.1,
          "yMax": 561.606
        },
        {
          "text": "员",
          "xMin": 138.336,
          "yMin": 550.686,
          "xMax": 148.836,
          "yMax": 561.606
        },
        {
          "text": "校内实践",
          "xMin": 223.9,
          "yMin": 436.681,
          "xMax": 279.9,
          "yMax": 451.241
        },
        {
          "text": "2.",
          "xMin": 280.85,
          "yMin": 431.971,
          "xMax": 290.772,
          "yMax": 443.411
        },
        {
          "text": "善用目标激励与情感激励，参赛小组至今仍保持团队",
          "xMin": 307.85,
          "yMin": 431.971,
          "xMax": 560.85,
          "yMax": 443.411
        },
        {
          "text": "文化。",
          "xMin": 259.85,
          "yMin": 449.971,
          "xMax": 292.85,
          "yMax": 461.411
        },
        {
          "text": "2013.09",
          "xMin": 223.85,
          "yMin": 473.271,
          "xMax": 272.25,
          "yMax": 484.711
        },
        {
          "text": "--",
          "xMin": 277.75,
          "yMin": 473.271,
          "xMax": 285.065,
          "yMax": 484.711
        },
        {
          "text": "2017.06",
          "xMin": 290.55,
          "yMin": 473.271,
          "xMax": 338.95,
          "yMax": 484.711
        },
        {
          "text": "湖工工程院会计系办公室",
          "xMin": 366.395,
          "yMin": 473.271,
          "xMax": 487.373,
          "yMax": 484.711
        },
        {
          "text": "行政助",
          "xMin": 531.285,
          "yMin": 473.271,
          "xMax": 564.285,
          "yMax": 484.711
        },
        {
          "text": "理",
          "xMin": 223.85,
          "yMin": 491.271,
          "xMax": 234.85,
          "yMax": 502.711
        },
        {
          "text": "工作描述：",
          "xMin": 223.85,
          "yMin": 515.271,
          "xMax": 278.85,
          "yMax": 526.711
        },
        {
          "text": "内务支持：负责收发传真复印、扫描文档、收发信件、文件、快递等；",
          "xMin": 223.85,
          "yMin": 533.271,
          "xMax": 564.85,
          "yMax": 544.711
        },
        {
          "text": "活动支持：负责学校员工活动，各会议安排、组织、文体活动安排等；",
          "xMin": 223.85,
          "yMin": 551.271,
          "xMax": 564.85,
          "yMax": 562.711
        },
        {
          "text": "邮",
          "xMin": 18.85,
          "yMin": 570.236,
          "xMax": 29.35,
          "yMax": 581.156
        },
        {
          "text": "箱",
          "xMin": 33.035,
          "yMin": 570.236,
          "xMax": 43.535,
          "yMax": 581.156
        },
        {
          "text": "：",
          "xMin": 47.221,
          "yMin": 570.236,
          "xMax": 57.721,
          "yMax": 581.156
        },
        {
          "text": "9393@qq.com",
          "xMin": 61.5,
          "yMin": 570.236,
          "xMax": 127.503,
          "yMax": 581.156
        },
        {
          "text": "地址：北京海淀苏州街",
          "xMin": 18.85,
          "yMin": 595.236,
          "xMax": 127.347,
          "yMax": 606.156
        },
        {
          "text": "专",
          "xMin": 37.3,
          "yMin": 634.273,
          "xMax": 51.3,
          "yMax": 651.871
        },
        {
          "text": "业",
          "xMin": 57.292,
          "yMin": 634.273,
          "xMax": 71.292,
          "yMax": 651.871
        },
        {
          "text": "技",
          "xMin": 77.284,
          "yMin": 634.273,
          "xMax": 91.284,
          "yMax": 651.871
        },
        {
          "text": "能",
          "xMin": 97.276,
          "yMin": 634.273,
          "xMax": 111.276,
          "yMax": 651.871
        },
        {
          "text": "证书奖励",
          "xMin": 223.9,
          "yMin": 590.881,
          "xMax": 279.9,
          "yMax": 605.441
        },
        {
          "text": "通用技能证书：",
          "xMin": 223.85,
          "yMin": 627.471,
          "xMax": 300.85,
          "yMax": 638.911
        },
        {
          "text": "英语四级证书、普通话二级甲等证书、机动车驾驶证",
          "xMin": 311.828,
          "yMin": 627.471,
          "xMax": 564.817,
          "yMax": 638.911
        },
        {
          "text": "专业技能证书：",
          "xMin": 223.85,
          "yMin": 645.471,
          "xMax": 300.85,
          "yMax": 656.911
        },
        {
          "text": "Adobe",
          "xMin": 311.85,
          "yMin": 645.471,
          "xMax": 342.056,
          "yMax": 656.911
        },
        {
          "text": "认证设计师资质，WPS",
          "xMin": 344.25,
          "yMin": 645.471,
          "xMax": 455.185,
          "yMax": 656.911
        },
        {
          "text": "年度最佳设计师",
          "xMin": 457.35,
          "yMin": 645.471,
          "xMax": 534.35,
          "yMax": 656.911
        },
        {
          "text": "活动荣誉奖励：",
          "xMin": 223.85,
          "yMin": 663.471,
          "xMax": 300.85,
          "yMax": 674.911
        },
        {
          "text": "2014",
          "xMin": 311.85,
          "yMin": 663.471,
          "xMax": 342.65,
          "yMax": 674.911
        },
        {
          "text": "年湖北省创青春创业计划移动专项赛银奖",
          "xMin": 344.85,
          "yMin": 663.471,
          "xMax": 542.85,
          "yMax": 674.911
        },
        {
          "text": "学习能力",
          "xMin": 13.2,
          "yMin": 693.261,
          "xMax": 45.2,
          "yMax": 701.581
        },
        {
          "text": "团队合作",
          "xMin": 13.2,
          "yMin": 718.261,
          "xMax": 45.2,
          "yMax": 726.581
        },
        {
          "text": "自我评价",
          "xMin": 223.9,
          "yMin": 720.581,
          "xMax": 279.9,
          "yMax": 735.141
        },
        {
          "text": "软件操作",
          "xMin": 13.2,
          "yMin": 743.261,
          "xMax": 45.2,
          "yMax": 751.581
        },
        {
          "text": "专业能力",
          "xMin": 13.2,
          "yMin": 768.261,
          "xMax": 45.2,
          "yMax": 776.581
        },
        {
          "text": "项目管理",
          "xMin": 13.2,
          "yMin": 793.261,
          "xMax": 45.2,
          "yMax": 801.581
        },
        {
          "text": "良好的公共关系意识，善于沟通，具备活动策划和组织协调能力。良好",
          "xMin": 223.85,
          "yMin": 757.171,
          "xMax": 564.85,
          "yMax": 768.611
        },
        {
          "text": "的心态和责任感，吃苦耐劳，擅于管理时间，勇于面对变化和挑战。良",
          "xMin": 223.85,
          "yMin": 775.171,
          "xMax": 564.85,
          "yMax": 786.611
        },
        {
          "text": "好的学习能力，习惯制定切实可行的学习计划，勤于学习能不断提高。",
          "xMin": 223.85,
          "yMin": 793.171,
          "xMax": 564.85,
          "yMax": 804.611
        }
      ]
    }
  ]
}